debian_crossgrader/__init__.py
debian_crossgrader/__main__.py
debian_crossgrader/arch-check-hook.sh
debian_crossgrader/crossgrader.py
debian_crossgrader/tools/__init__.py
debian_crossgrader/tools/package_check.py
debian_crossgrader/tools/random_install.py
debian_crossgrader/utils/__init__.py
debian_crossgrader/utils/apt.py
debian_crossgrader/utils/cmd.py
debian_crossgrader/utils/elf.py
debian_crossgrader/utils/shells.py
debian_crossgrader-0.0.3.dist-info/LICENSE.txt
debian_crossgrader-0.0.3.dist-info/METADATA
debian_crossgrader-0.0.3.dist-info/WHEEL
debian_crossgrader-0.0.3.dist-info/entry_points.txt
debian_crossgrader-0.0.3.dist-info/top_level.txt
debian_crossgrader-0.0.3.dist-info/RECORD
