Metadata-Version: 2.1
Name: debian-crossgrader
Version: 0.0.3
Summary: Debian crossgrading tool
Home-page: https://salsa.debian.org/crossgrading-team/debian-crossgrading
Author: Kevin Wu
Author-email: kevin@kevinniuwu.com
License: GPL-2+
Platform: Debian
Classifier: Programming Language :: Python :: 3
Classifier: Operating System :: POSIX :: Linux
Classifier: License :: OSI Approved :: GNU General Public License v2 or later (GPLv2+)
Requires-Python: >=3.4
Requires-Dist: appdirs
Requires-Dist: python-apt (>=1.0.0)
